{
  "id": "3363448",
  "name": "ifalse.cn",
  "font_family": "iconfont",
  "css_prefix_text": "icon-",
  "description": "",
  "glyphs": [
    {
      "icon_id": "670208",
      "name": "YDUI-正确(实心)",
      "font_class": "yduizhengqueshixin",
      "unicode": "e6a9",
      "unicode_decimal": 59049
    },
    {
      "icon_id": "11487985",
      "name": "atm",
      "font_class": "atm",
      "unicode": "e744",
      "unicode_decimal": 59204
    },
    {
      "icon_id": "11487988",
      "name": "browse",
      "font_class": "browse",
      "unicode": "e745",
      "unicode_decimal": 59205
    },
    {
      "icon_id": "11488038",
      "name": "email",
      "font_class": "email",
      "unicode": "e74f",
      "unicode_decimal": 59215
    },
    {
      "icon_id": "11488087",
      "name": "password",
      "font_class": "password",
      "unicode": "e75b",
      "unicode_decimal": 59227
    },
    {
      "icon_id": "11488088",
      "name": "Not visible",
      "font_class": "Notvisible",
      "unicode": "e75a",
      "unicode_decimal": 59226
    },
    {
      "icon_id": "201552",
      "name": "列表模式",
      "font_class": "liebiaomoshi",
      "unicode": "e601",
      "unicode_decimal": 58881
    },
    {
      "icon_id": "26827155",
      "name": "置顶",
      "font_class": "zhiding3",
      "unicode": "e628",
      "unicode_decimal": 58920
    },
    {
      "icon_id": "278286",
      "name": "home",
      "font_class": "home",
      "unicode": "e626",
      "unicode_decimal": 58918
    },
    {
      "icon_id": "557041",
      "name": "xiaoxi",
      "font_class": "xiaoxi",
      "unicode": "e625",
      "unicode_decimal": 58917
    },
    {
      "icon_id": "6616997",
      "name": "关闭",
      "font_class": "guanbi",
      "unicode": "eca0",
      "unicode_decimal": 60576
    },
    {
      "icon_id": "705699",
      "name": "指南针",
      "font_class": "zhinanzhen",
      "unicode": "e630",
      "unicode_decimal": 58928
    },
    {
      "icon_id": "11372742",
      "name": "指纹",
      "font_class": "zhiwen",
      "unicode": "e8c2",
      "unicode_decimal": 59586
    },
    {
      "icon_id": "8084546",
      "name": "查看",
      "font_class": "chakan",
      "unicode": "e613",
      "unicode_decimal": 58899
    },
    {
      "icon_id": "8639849",
      "name": "退出",
      "font_class": "tuichu",
      "unicode": "e600",
      "unicode_decimal": 58880
    },
    {
      "icon_id": "12004325",
      "name": "User",
      "font_class": "User",
      "unicode": "ea94",
      "unicode_decimal": 60052
    },
    {
      "icon_id": "7155227",
      "name": "菜单",
      "font_class": "caidan",
      "unicode": "e652",
      "unicode_decimal": 58962
    },
    {
      "icon_id": "577365",
      "name": "搜索",
      "font_class": "sousuo",
      "unicode": "e752",
      "unicode_decimal": 59218
    }
  ]
}
